{
  "patch_id": "9d0db06a-a6cd-488b-8ad4-413ab0092887",
  "timestamp": "2025-10-15T04:37:11.421146",
  "author": "Juanito",
  "diff": {
    "animation": {
      "rbxassetid://8249271040": {
        "status": "modified",
        "changes": {
          "hitbox": {
            "from": {
              "Y": 10,
              "X": 20,
              "Z": 15
            },
            "to": {
              "Y": 10,
              "X": 23,
              "Z": 15
            }
          }
        }
      }
    }
  }
}